dillema/__init__.py
dillema/__main__.py
dillema/cli.py
dillema/common.py
dillema/example.py
dillema/utils.py
dillema/api/__init__.py
dillema/api/server.py
dillema/models/__init__.py
dillema/models/model.py
dillema/ray_cluster/__init__.py
dillema/ray_cluster/client_node.py
dillema/ray_cluster/head_node.py
dillema/tests/__init__.py
dillema/vllm/__init__.py
dillema/workers/__init__.py
test/__init__.py
test/test_example.py
dillema-0.1.6.dist-info/LICENSE
dillema-0.1.6.dist-info/METADATA
dillema-0.1.6.dist-info/WHEEL
dillema-0.1.6.dist-info/top_level.txt
dillema-0.1.6.dist-info/RECORD
