Metadata-Version: 2.2
Name: DiLLeMa
Version: 0.1.6
Summary: This repository contains a docker-compose file that can be used to run a Ray cluster on a single machine
Author-email: Robby Ulung Pambudi <robby.pambudi10@gmail.com>
License: MIT
Project-URL: Homepage, https://github.com/robbypambudi/DiLLeMa
Requires-Python: ==3.12.9
License-File: LICENSE
Requires-Dist: vllm==0.7.3
Requires-Dist: ray==2.40.0
Requires-Dist: ray[default]
